CRC/sumador_restador/sumador1.v
module sumador_1 (
    input A,
    input B,
    input Ci,
    output So,
    output Co 
);
    
    assign So = A ^ (B ^ Ci);
    assign Co = (Ci & (A ^ B)) | (A & B);

endmodule

CRC/sumador_restador/sumador_4bits.v
`include "sumador1.v"
module sumador_4bits(
    input [3:0] A,
    input [3:0] B,
    input Ci,
    output [3:0] S,
    output Co 
);
    
    wire c1, c2, c3;

    
    sumador_1 bit0 (
        .A(A[0]), 
        .B(B[0]), 
        .Ci(Ci), 
        .So(S[0]), 
        .Co(c1)    // El acarreo sale hacia c1
    );

    // Instancia 1
    sumador_1 bit1 (
        .A(A[1]), 
        .B(B[1]), 
        .Ci(c1),   // Entra el acarreo c1
        .So(S[1]), 
        .Co(c2)    // El acarreo sale hacia c2
    );

    // Instancia 2
    sumador_1 bit2 (
        .A(A[2]), 
        .B(B[2]), 
        .Ci(c2),   // Entra el acarreo c2
        .So(S[2]), 
        .Co(c3)    // El acarreo sale hacia c3
    );

    // Instancia 3: Bit más significativo (MSB)
    sumador_1 bit3 (
        .A(A[3]), 
        .B(B[3]), 
        .Ci(c3),   // Entra el acarreo c3
        .So(S[3]), 
        .Co(Co)    // El acarreo final sale al exterior del módulo
    );

endmodule

CRC/sumador_restador/sumador_restador.v
`include "sumador_4bits.v"
module sumador_restador(
    input [3:0] A,
    input [3:0] B,
    input Sel,       // 0 = Suma, 1 = Resta
    output [3:0] S,
    output Co
);

    wire [3:0] B_xor;

    // Lógica para invertir B si estamos restando (Complemento a 1)
    assign B_xor[0] = B[0] ^ Sel;
    assign B_xor[1] = B[1] ^ Sel;
    assign B_xor[2] = B[2] ^ Sel;
    assign B_xor[3] = B[3] ^ Sel;

    // Instanciamos el sumador de 4 bits
    sumador_4bits mi_sumador (
        .A(A),
        .B(B_xor),   // Entra B normal o invertido
        .Ci(Sel),    // Sumamos 1 al Carry In si Sel=1 (Completa el complemento a 2)
        .S(S),
        .Co(Co)
    );

endmodule

CRC/sumador_restador/sumador_restador_tb.v
`timescale 1s / 1s
`include "sumador_restador.v"

module tb_sumador_restador;

    
    reg [3:0] A;
    reg [3:0] B;
    reg Sel;

    
    wire [3:0] S;
    wire Co;

    
    integer i, j;

    
    sumador_restador uut (
        .A(A),
        .B(B),
        .Sel(Sel),
        .S(S),
        .Co(Co)
    );

    initial begin
        
        $dumpfile("simulacion_total.vcd");
        $dumpvars(0, tb_sumador_restador);

      
        $display("--- INICIANDO TODAS LAS SUMAS (Sel = 0) ---");
        Sel = 0;
        
        
        for (i = 0; i < 16; i = i + 1) begin
            
            for (j = 0; j < 16; j = j + 1) begin
                A = i[3:0]; 
                B = j[3:0];
                #5; 
            end
        end

        
        $display("\n--- INICIANDO TODAS LAS RESTAS (Sel = 1) ---");
        Sel = 1;
        
        for (i = 0; i < 16; i = i + 1) begin
            for (j = 0; j < 16; j = j + 1) begin
                A = i[3:0];
                B = j[3:0];
                #5;
            end
        end

        
        $display("\n--- SIMULACION TERMINADA EXITOSAMENTE ---");
        $finish;
    end

    
    initial begin
        $monitor("Tiempo=%0t | Sel=%b | A=%d, B=%d | Resultado(S)=%b (Dec:%d), Co=%b", 
                 $time, Sel, A, B, S, S, Co);
    end

endmodule

CRC/sumador_restador/build/simulacion_total.vcd
$date
	Thu Mar 12 19:08:07 2026
$end
$version
	Icarus Verilog
$end
$timescale
	1s
$end
$scope module tb_sumador_restador $end
$var wire 4 ! S [3:0] $end
$var wire 1 " Co $end
$var reg 4 # A [3:0] $end
$var reg 4 $ B [3:0] $end
$var reg 1 % Sel $end
$var integer 32 & i [31:0] $end
$var integer 32 ' j [31:0] $end
$scope module uut $end
$var wire 4 ( A [3:0] $end
$var wire 4 ) B [3:0] $end
$var wire 1 % Sel $end
$var wire 4 * S [3:0] $end
$var wire 1 " Co $end
$var wire 4 + B_xor [3:0] $end
$scope module mi_sumador $end
$var wire 4 , A [3:0] $end
$var wire 4 - B [3:0] $end
$var wire 1 % Ci $end
$var wire 1 . c3 $end
$var wire 1 / c2 $end
$var wire 1 0 c1 $end
$var wire 4 1 S [3:0] $end
$var wire 1 " Co $end
$scope module bit0 $end
$var wire 1 2 A $end
$var wire 1 3 B $end
$var wire 1 % Ci $end
$var wire 1 0 Co $end
$var wire 1 4 So $end
$upscope $end
$scope module bit1 $end
$var wire 1 5 A $end
$var wire 1 6 B $end
$var wire 1 0 Ci $end
$var wire 1 / Co $end
$var wire 1 7 So $end
$upscope $end
$scope module bit2 $end
$var wire 1 8 A $end
$var wire 1 9 B $end
$var wire 1 / Ci $end
$var wire 1 . Co $end
$var wire 1 : So $end
$upscope $end
$scope module bit3 $end
$var wire 1 ; A $end
$var wire 1 < B $end
$var wire 1 . Ci $end
$var wire 1 " Co $end
$var wire 1 = So $end
$upscope $end
$upscope $end
$upscope $end
$upscope $end
$enddefinitions $end
$comment Show the parameter values. $end
$dumpall
$end
#0
$dumpvars
0=
0<
0;
0:
09
08
07
06
05
04
03
02
b0 1
00
0/
0.
b0 -
b0 ,
b0 +
b0 *
b0 )
b0 (
b0 '
b0 &
0%
b0 $
b0 #
0"
b0 !
$end
#5
b1 !
b1 *
b1 1
14
13
b1 +
b1 -
b1 $
b1 )
b1 '
#10
04
b10 !
b10 *
b10 1
17
03
16
b10 +
b10 -
b10 $
b10 )
b10 '
#15
b11 !
b11 *
b11 1
14
13
b11 +
b11 -
b11 $
b11 )
b11 '
#20
04
07
b100 !
b100 *
b100 1
1:
03
06
19
b100 +
b100 -
b100 $
b100 )
b100 '
#25
b101 !
b101 *
b101 1
14
13
b101 +
b101 -
b101 $
b101 )
b101 '
#30
04
b110 !
b110 *
b110 1
17
03
16
b110 +
b110 -
b110 $
b110 )
b110 '
#35
b111 !
b111 *
b111 1
14
13
b111 +
b111 -
b111 $
b111 )
b111 '
#40
04
07
0:
b1000 !
b1000 *
b1000 1
1=
03
06
09
1<
b1000 +
b1000 -
b1000 $
b1000 )
b1000 '
#45
b1001 !
b1001 *
b1001 1
14
13
b1001 +
b1001 -
b1001 $
b1001 )
b1001 '
#50
04
b1010 !
b1010 *
b1010 1
17
03
16
b1010 +
b1010 -
b1010 $
b1010 )
b1010 '
#55
b1011 !
b1011 *
b1011 1
14
13
b1011 +
b1011 -
b1011 $
b1011 )
b1011 '
#60
04
07
b1100 !
b1100 *
b1100 1
1:
03
06
19
b1100 +
b1100 -
b1100 $
b1100 )
b1100 '
#65
b1101 !
b1101 *
b1101 1
14
13
b1101 +
b1101 -
b1101 $
b1101 )
b1101 '
#70
04
b1110 !
b1110 *
b1110 1
17
03
16
b1110 +
b1110 -
b1110 $
b1110 )
b1110 '
#75
b1111 !
b1111 *
b1111 1
14
13
b1111 +
b1111 -
b1111 $
b1111 )
b1111 '
#80
07
0:
0=
0/
03
06
09
0<
00
b0 +
b0 -
b1 !
b1 *
b1 1
14
12
b0 $
b0 )
b1 #
b1 (
b1 ,
b1 &
b0 '
#85
17
b10 !
b10 *
b10 1
04
10
13
b1 +
b1 -
b1 $
b1 )
b1 '
#90
0:
0/
14
00
b11 !
b11 *
b11 1
17
03
16
b10 +
b10 -
b10 $
b10 )
b10 '
#95
1:
07
1/
b100 !
b100 *
b100 1
04
10
13
b11 +
b11 -
b11 $
b11 )
b11 '
#100
0=
0/
0.
14
00
07
b101 !
b101 *
b101 1
1:
03
06
19
b100 +
b100 -
b100 $
b100 )
b100 '
#105
17
b110 !
b110 *
b110 1
04
10
13
b101 +
b101 -
b101 $
b101 )
b101 '
#110
0=
1:
0.
0/
14
00
b111 !
b111 *
b111 1
17
03
16
b110 +
b110 -
b110 $
b110 )
b110 '
#115
1=
0:
1.
07
1/
b1000 !
b1000 *
b1000 1
04
10
13
b111 +
b111 -
b111 $
b111 )
b111 '
#120
0/
0.
0"
14
00
07
0:
b1001 !
b1001 *
b1001 1
1=
03
06
09
1<
b1000 +
b1000 -
b1000 $
b1000 )
b1000 '
#125
17
b1010 !
b1010 *
b1010 1
04
10
13
b1001 +
b1001 -
b1001 $
b1001 )
b1001 '
#130
0:
0/
14
00
b1011 !
b1011 *
b1011 1
17
03
16
b1010 +
b1010 -
b1010 $
b1010 )
b1010 '
#135
1:
07
1/
b1100 !
b1100 *
b1100 1
04
10
13
b1011 +
b1011 -
b1011 $
b1011 )
b1011 '
#140
1=
0"
0/
0.
14
00
07
b1101 !
b1101 *
b1101 1
1:
03
06
19
b1100 +
b1100 -
b1100 $
b1100 )
b1100 '
#145
17
b1110 !
b1110 *
b1110 1
04
10
13
b1101 +
b1101 -
b1101 $
b1101 )
b1101 '
#150
1=
0"
1:
0.
0/
14
00
b1111 !
b1111 *
b1111 1
17
03
16
b1110 +
b1110 -
b1110 $
b1110 )
b1110 '
#155
0=
1"
0:
1.
07
1/
b0 !
b0 *
b0 1
04
10
13
b1111 +
b1111 -
b1111 $
b1111 )
b1111 '
#160
0.
0"
0/
0:
0=
03
06
09
0<
00
b0 +
b0 -
04
b10 !
b10 *
b10 1
17
02
15
b0 $
b0 )
b10 #
b10 (
b10 ,
b10 &
b0 '
#165
b11 !
b11 *
b11 1
14
13
b1 +
b1 -
b1 $
b1 )
b1 '
#170
1:
04
b100 !
b100 *
b100 1
07
1/
03
16
b10 +
b10 -
b10 $
b10 )
b10 '
#175
b101 !
b101 *
b101 1
14
13
b11 +
b11 -
b11 $
b11 )
b11 '
#180
0=
0.
04
17
0/
b110 !
b110 *
b110 1
1:
03
06
19
b100 +
b100 -
b100 $
b100 )
b100 '
#185
b111 !
b111 *
b111 1
14
13
b101 +
b101 -
b101 $
b101 )
b101 '
#190
1=
0:
1.
04
b1000 !
b1000 *
b1000 1
07
1/
03
16
b110 +
b110 -
b110 $
b110 )
b110 '
#195
b1001 !
b1001 *
b1001 1
14
13
b111 +
b111 -
b111 $
b111 )
b111 '
#200
0.
0"
04
17
0/
0:
b1010 !
b1010 *
b1010 1
1=
03
06
09
1<
b1000 +
b1000 -
b1000 $
b1000 )
b1000 '
#205
b1011 !
b1011 *
b1011 1
14
13
b1001 +
b1001 -
b1001 $
b1001 )
b1001 '
#210
1:
04
b1100 !
b1100 *
b1100 1
07
1/
03
16
b1010 +
b1010 -
b1010 $
b1010 )
b1010 '
#215
b1101 !
b1101 *
b1101 1
14
13
b1011 +
b1011 -
b1011 $
b1011 )
b1011 '
#220
1=
0"
0.
04
17
0/
b1110 !
b1110 *
b1110 1
1:
03
06
19
b1100 +
b1100 -
b1100 $
b1100 )
b1100 '
#225
b1111 !
b1111 *
b1111 1
14
13
b1101 +
b1101 -
b1101 $
b1101 )
b1101 '
#230
0=
1"
0:
1.
04
b0 !
b0 *
b0 1
07
1/
03
16
b1110 +
b1110 -
b1110 $
b1110 )
b1110 '
#235
b1 !
b1 *
b1 1
14
13
b1111 +
b1111 -
b1111 $
b1111 )
b1111 '
#240
17
0.
0"
0/
0:
0=
03
06
09
0<
00
b0 +
b0 -
b11 !
b11 *
b11 1
14
12
b0 $
b0 )
b11 #
b11 (
b11 ,
b11 &
b0 '
#245
1:
07
1/
b100 !
b100 *
b100 1
04
10
13
b1 +
b1 -
b1 $
b1 )
b1 '
#250
14
00
b101 !
b101 *
b101 1
07
03
16
b10 +
b10 -
b10 $
b10 )
b10 '
#255
17
b110 !
b110 *
b110 1
04
10
13
b11 +
b11 -
b11 $
b11 )
b11 '
#260
0=
0.
14
00
17
0/
b111 !
b111 *
b111 1
1:
03
06
19
b100 +
b100 -
b100 $
b100 )
b100 '
#265
1=
0:
1.
07
1/
b1000 !
b1000 *
b1000 1
04
10
13
b101 +
b101 -
b101 $
b101 )
b101 '
#270
14
00
b1001 !
b1001 *
b1001 1
07
03
16
b110 +
b110 -
b110 $
b110 )
b110 '
#275
17
b1010 !
b1010 *
b1010 1
04
10
13
b111 +
b111 -
b111 $
b111 )
b111 '
#280
0.
0"
14
00
17
0/
0:
b1011 !
b1011 *
b1011 1
1=
03
06
09
1<
b1000 +
b1000 -
b1000 $
b1000 )
b1000 '
#285
1:
07
1/
b1100 !
b1100 *
b1100 1
04
10
13
b1001 +
b1001 -
b1001 $
b1001 )
b1001 '
#290
14
00
b1101 !
b1101 *
b1101 1
07
03
16
b1010 +
b1010 -
b1010 $
b1010 )
b1010 '
#295
17
b1110 !
b1110 *
b1110 1
04
10
13
b1011 +
b1011 -
b1011 $
b1011 )
b1011 '
#300
1=
0"
0.
14
00
17
0/
b1111 !
b1111 *
b1111 1
1:
03
06
19
b1100 +
b1100 -
b1100 $
b1100 )
b1100 '
#305
0=
1"
0:
1.
07
1/
b0 !
b0 *
b0 1
04
10
13
b1101 +
b1101 -
b1101 $
b1101 )
b1101 '
#310
14
00
b1 !
b1 *
b1 1
07
03
16
b1110 +
b1110 -
b1110 $
b1110 )
b1110 '
#315
17
b10 !
b10 *
b10 1
04
10
13
b1111 +
b1111 -
b1111 $
b1111 )
b1111 '
#320
0.
0"
0=
03
06
09
0<
00
0/
b0 +
b0 -
04
07
b100 !
b100 *
b100 1
1:
02
05
18
b0 $
b0 )
b100 #
b100 (
b100 ,
b100 &
b0 '
#325
b101 !
b101 *
b101 1
14
13
b1 +
b1 -
b1 $
b1 )
b1 '
#330
04
b110 !
b110 *
b110 1
17
03
16
b10 +
b10 -
b10 $
b10 )
b10 '
#335
b111 !
b111 *
b111 1
14
13
b11 +
b11 -
b11 $
b11 )
b11 '
#340
1=
04
07
b1000 !
b1000 *
b1000 1
0:
1.
03
06
19
b100 +
b100 -
b100 $
b100 )
b100 '
#345
b1001 !
b1001 *
b1001 1
14
13
b101 +
b101 -
b101 $
b101 )
b101 '
#350
04
b1010 !
b1010 *
b1010 1
17
03
16
b110 +
b110 -
b110 $
b110 )
b110 '
#355
b1011 !
b1011 *
b1011 1
14
13
b111 +
b111 -
b111 $
b111 )
b111 '
#360
0"
04
07
1:
0.
b1100 !
b1100 *
b1100 1
1=
03
06
09
1<
b1000 +
b1000 -
b1000 $
b1000 )
b1000 '
#365
b1101 !
b1101 *
b1101 1
14
13
b1001 +
b1001 -
b1001 $
b1001 )
b1001 '
#370
04
b1110 !
b1110 *
b1110 1
17
03
16
b1010 +
b1010 -
b1010 $
b1010 )
b1010 '
#375
b1111 !
b1111 *
b1111 1
14
13
b1011 +
b1011 -
b1011 $
b1011 )
b1011 '
#380
0=
1"
04
07
b0 !
b0 *
b0 1
0:
1.
03
06
19
b1100 +
b1100 -
b1100 $
b1100 )
b1100 '
#385
b1 !
b1 *
b1 1
14
13
b1101 +
b1101 -
b1101 $
b1101 )
b1101 '
#390
04
b10 !
b10 *
b10 1
17
03
16
b1110 +
b1110 -
b1110 $
b1110 )
b1110 '
#395
b11 !
b11 *
b11 1
14
13
b1111 +
b1111 -
b1111 $
b1111 )
b1111 '
#400
07
0"
1:
0.
0=
0/
03
06
09
0<
00
b0 +
b0 -
b101 !
b101 *
b101 1
14
12
b0 $
b0 )
b101 #
b101 (
b101 ,
b101 &
b0 '
#405
17
b110 !
b110 *
b110 1
04
10
13
b1 +
b1 -
b1 $
b1 )
b1 '
#410
0=
1:
0.
0/
14
00
b111 !
b111 *
b111 1
17
03
16
b10 +
b10 -
b10 $
b10 )
b10 '
#415
1=
0:
1.
07
1/
b1000 !
b1000 *
b1000 1
04
10
13
b11 +
b11 -
b11 $
b11 )
b11 '
#420
0/
14
00
07
b1001 !
b1001 *
b1001 1
0:
03
06
19
b100 +
b100 -
b100 $
b100 )
b100 '
#425
17
b1010 !
b1010 *
b1010 1
04
10
13
b101 +
b101 -
b101 $
b101 )
b101 '
#430
0:
0/
14
00
b1011 !
b1011 *
b1011 1
17
03
16
b110 +
b110 -
b110 $
b110 )
b110 '
#435
1:
07
1/
b1100 !
b1100 *
b1100 1
04
10
13
b111 +
b111 -
b111 $
b111 )
b111 '
#440
0/
0"
14
00
07
1:
0.
b1101 !
b1101 *
b1101 1
1=
03
06
09
1<
b1000 +
b1000 -
b1000 $
b1000 )
b1000 '
#445
17
b1110 !
b1110 *
b1110 1
04
10
13
b1001 +
b1001 -
b1001 $
b1001 )
b1001 '
#450
1=
0"
1:
0.
0/
14
00
b1111 !
b1111 *
b1111 1
17
03
16
b1010 +
b1010 -
b1010 $
b1010 )
b1010 '
#455
0=
1"
0:
1.
07
1/
b0 !
b0 *
b0 1
04
10
13
b1011 +
b1011 -
b1011 $
b1011 )
b1011 '
#460
0/
14
00
07
b1 !
b1 *
b1 1
0:
03
06
19
b1100 +
b1100 -
b1100 $
b1100 )
b1100 '
#465
17
b10 !
b10 *
b10 1
04
10
13
b1101 +
b1101 -
b1101 $
b1101 )
b1101 '
#470
0:
0/
14
00
b11 !
b11 *
b11 1
17
03
16
b1110 +
b1110 -
b1110 $
b1110 )
b1110 '
#475
1:
07
1/
b100 !
b100 *
b100 1
04
10
13
b1111 +
b1111 -
b1111 $
b1111 )
b1111 '
#480
0"
0/
1:
0.
0=
03
06
09
0<
00
b0 +
b0 -
04
b110 !
b110 *
b110 1
17
02
15
b0 $
b0 )
b110 #
b110 (
b110 ,
b110 &
b0 '
#485
b111 !
b111 *
b111 1
14
13
b1 +
b1 -
b1 $
b1 )
b1 '
#490
1=
0:
1.
04
b1000 !
b1000 *
b1000 1
07
1/
03
16
b10 +
b10 -
b10 $
b10 )
b10 '
#495
b1001 !
b1001 *
b1001 1
14
13
b11 +
b11 -
b11 $
b11 )
b11 '
#500
04
17
0/
b1010 !
b1010 *
b1010 1
0:
03
06
19
b100 +
b100 -
b100 $
b100 )
b100 '
#505
b1011 !
b1011 *
b1011 1
14
13
b101 +
b101 -
b101 $
b101 )
b101 '
#510
1:
04
b1100 !
b1100 *
b1100 1
07
1/
03
16
b110 +
b110 -
b110 $
b110 )
b110 '
#515
b1101 !
b1101 *
b1101 1
14
13
b111 +
b111 -
b111 $
b111 )
b111 '
#520
0"
04
17
0/
1:
0.
b1110 !
b1110 *
b1110 1
1=
03
06
09
1<
b1000 +
b1000 -
b1000 $
b1000 )
b1000 '
#525
b1111 !
b1111 *
b1111 1
14
13
b1001 +
b1001 -
b1001 $
b1001 )
b1001 '
#530
0=
1"
0:
1.
04
b0 !
b0 *
b0 1
07
1/
03
16
b1010 +
b1010 -
b1010 $
b1010 )
b1010 '
#535
b1 !
b1 *
b1 1
14
13
b1011 +
b1011 -
b1011 $
b1011 )
b1011 '
#540
04
17
0/
b10 !
b10 *
b10 1
0:
03
06
19
b1100 +
b1100 -
b1100 $
b1100 )
b1100 '
#545
b11 !
b11 *
b11 1
14
13
b1101 +
b1101 -
b1101 $
b1101 )
b1101 '
#550
1:
04
b100 !
b100 *
b100 1
07
1/
03
16
b1110 +
b1110 -
b1110 $
b1110 )
b1110 '
#555
b101 !
b101 *
b101 1
14
13
b1111 +
b1111 -
b1111 $
b1111 )
b1111 '
#560
17
0"
0/
1:
0.
0=
03
06
09
0<
00
b0 +
b0 -
b111 !
b111 *
b111 1
14
12
b0 $
b0 )
b111 #
b111 (
b111 ,
b111 &
b0 '
#565
1=
0:
1.
07
1/
b1000 !
b1000 *
b1000 1
04
10
13
b1 +
b1 -
b1 $
b1 )
b1 '
#570
14
00
b1001 !
b1001 *
b1001 1
07
03
16
b10 +
b10 -
b10 $
b10 )
b10 '
#575
17
b1010 !
b1010 *
b1010 1
04
10
13
b11 +
b11 -
b11 $
b11 )
b11 '
#580
14
00
17
0/
b1011 !
b1011 *
b1011 1
0:
03
06
19
b100 +
b100 -
b100 $
b100 )
b100 '
#585
1:
07
1/
b1100 !
b1100 *
b1100 1
04
10
13
b101 +
b101 -
b101 $
b101 )
b101 '
#590
14
00
b1101 !
b1101 *
b1101 1
07
03
16
b110 +
b110 -
b110 $
b110 )
b110 '
#595
17
b1110 !
b1110 *
b1110 1
04
10
13
b111 +
b111 -
b111 $
b111 )
b111 '
#600
0"
14
00
17
0/
1:
0.
b1111 !
b1111 *
b1111 1
1=
03
06
09
1<
b1000 +
b1000 -
b1000 $
b1000 )
b1000 '
#605
0=
1"
0:
1.
07
1/
b0 !
b0 *
b0 1
04
10
13
b1001 +
b1001 -
b1001 $
b1001 )
b1001 '
#610
14
00
b1 !
b1 *
b1 1
07
03
16
b1010 +
b1010 -
b1010 $
b1010 )
b1010 '
#615
17
b10 !
b10 *
b10 1
04
10
13
b1011 +
b1011 -
b1011 $
b1011 )
b1011 '
#620
14
00
17
0/
b11 !
b11 *
b11 1
0:
03
06
19
b1100 +
b1100 -
b1100 $
b1100 )
b1100 '
#625
1:
07
1/
b100 !
b100 *
b100 1
04
10
13
b1101 +
b1101 -
b1101 $
b1101 )
b1101 '
#630
14
00
b101 !
b101 *
b101 1
07
03
16
b1110 +
b1110 -
b1110 $
b1110 )
b1110 '
#635
17
b110 !
b110 *
b110 1
04
10
13
b1111 +
b1111 -
b1111 $
b1111 )
b1111 '
#640
0"
03
06
09
0<
00
0/
0.
b0 +
b0 -
04
07
0:
b1000 !
b1000 *
b1000 1
1=
02
05
08
1;
b0 $
b0 )
b1000 #
b1000 (
b1000 ,
b1000 &
b0 '
#645
b1001 !
b1001 *
b1001 1
14
13
b1 +
b1 -
b1 $
b1 )
b1 '
#650
04
b1010 !
b1010 *
b1010 1
17
03
16
b10 +
b10 -
b10 $
b10 )
b10 '
#655
b1011 !
b1011 *
b1011 1
14
13
b11 +
b11 -
b11 $
b11 )
b11 '
#660
04
07
b1100 !
b1100 *
b1100 1
1:
03
06
19
b100 +
b100 -
b100 $
b100 )
b100 '
#665
b1101 !
b1101 *
b1101 1
14
13
b101 +
b101 -
b101 $
b101 )
b101 '
#670
04
b1110 !
b1110 *
b1110 1
17
03
16
b110 +
b110 -
b110 $
b110 )
b110 '
#675
b1111 !
b1111 *
b1111 1
14
13
b111 +
b111 -
b111 $
b111 )
b111 '
#680
04
07
0:
b0 !
b0 *
b0 1
0=
1"
03
06
09
1<
b1000 +
b1000 -
b1000 $
b1000 )
b1000 '
#685
b1 !
b1 *
b1 1
14
13
b1001 +
b1001 -
b1001 $
b1001 )
b1001 '
#690
04
b10 !
b10 *
b10 1
17
03
16
b1010 +
b1010 -
b1010 $
b1010 )
b1010 '
#695
b11 !
b11 *
b11 1
14
13
b1011 +
b1011 -
b1011 $
b1011 )
b1011 '
#700
04
07
b100 !
b100 *
b100 1
1:
03
06
19
b1100 +
b1100 -
b1100 $
b1100 )
b1100 '
#705
b101 !
b101 *
b101 1
14
13
b1101 +
b1101 -
b1101 $
b1101 )
b1101 '
#710
04
b110 !
b110 *
b110 1
17
03
16
b1110 +
b1110 -
b1110 $
b1110 )
b1110 '
#715
b111 !
b111 *
b111 1
14
13
b1111 +
b1111 -
b1111 $
b1111 )
b1111 '
#720
07
0:
1=
0"
0/
03
06
09
0<
00
b0 +
b0 -
b1001 !
b1001 *
b1001 1
14
12
b0 $
b0 )
b1001 #
b1001 (
b1001 ,
b1001 &
b0 '
#725
17
b1010 !
b1010 *
b1010 1
04
10
13
b1 +
b1 -
b1 $
b1 )
b1 '
#730
0:
0/
14
00
b1011 !
b1011 *
b1011 1
17
03
16
b10 +
b10 -
b10 $
b10 )
b10 '
#735
1:
07
1/
b1100 !
b1100 *
b1100 1
04
10
13
b11 +
b11 -
b11 $
b11 )
b11 '
#740
1=
0"
0/
0.
14
00
07
b1101 !
b1101 *
b1101 1
1:
03
06
19
b100 +
b100 -
b100 $
b100 )
b100 '
#745
17
b1110 !
b1110 *
b1110 1
04
10
13
b101 +
b101 -
b101 $
b101 )
b101 '
#750
1=
0"
1:
0.
0/
14
00
b1111 !
b1111 *
b1111 1
17
03
16
b110 +
b110 -
b110 $
b110 )
b110 '
#755
0=
1"
0:
1.
07
1/
b0 !
b0 *
b0 1
04
10
13
b111 +
b111 -
b111 $
b111 )
b111 '
#760
0/
0.
14
00
07
0:
b1 !
b1 *
b1 1
0=
03
06
09
1<
b1000 +
b1000 -
b1000 $
b1000 )
b1000 '
#765
17
b10 !
b10 *
b10 1
04
10
13
b1001 +
b1001 -
b1001 $
b1001 )
b1001 '
#770
0:
0/
14
00
b11 !
b11 *
b11 1
17
03
16
b1010 +
b1010 -
b1010 $
b1010 )
b1010 '
#775
1:
07
1/
b100 !
b100 *
b100 1
04
10
13
b1011 +
b1011 -
b1011 $
b1011 )
b1011 '
#780
0=
0/
0.
14
00
07
b101 !
b101 *
b101 1
1:
03
06
19
b1100 +
b1100 -
b1100 $
b1100 )
b1100 '
#785
17
b110 !
b110 *
b110 1
04
10
13
b1101 +
b1101 -
b1101 $
b1101 )
b1101 '
#790
0=
1:
0.
0/
14
00
b111 !
b111 *
b111 1
17
03
16
b1110 +
b1110 -
b1110 $
b1110 )
b1110 '
#795
1=
0:
1.
07
1/
b1000 !
b1000 *
b1000 1
04
10
13
b1111 +
b1111 -
b1111 $
b1111 )
b1111 '
#800
0.
0/
0:
1=
0"
03
06
09
0<
00
b0 +
b0 -
04
b1010 !
b1010 *
b1010 1
17
02
15
b0 $
b0 )
b1010 #
b1010 (
b1010 ,
b1010 &
b0 '
#805
b1011 !
b1011 *
b1011 1
14
13
b1 +
b1 -
b1 $
b1 )
b1 '
#810
1:
04
b1100 !
b1100 *
b1100 1
07
1/
03
16
b10 +
b10 -
b10 $
b10 )
b10 '
#815
b1101 !
b1101 *
b1101 1
14
13
b11 +
b11 -
b11 $
b11 )
b11 '
#820
1=
0"
0.
04
17
0/
b1110 !
b1110 *
b1110 1
1:
03
06
19
b100 +
b100 -
b100 $
b100 )
b100 '
#825
b1111 !
b1111 *
b1111 1
14
13
b101 +
b101 -
b101 $
b101 )
b101 '
#830
0=
1"
0:
1.
04
b0 !
b0 *
b0 1
07
1/
03
16
b110 +
b110 -
b110 $
b110 )
b110 '
#835
b1 !
b1 *
b1 1
14
13
b111 +
b111 -
b111 $
b111 )
b111 '
#840
0.
04
17
0/
0:
b10 !
b10 *
b10 1
0=
03
06
09
1<
b1000 +
b1000 -
b1000 $
b1000 )
b1000 '
#845
b11 !
b11 *
b11 1
14
13
b1001 +
b1001 -
b1001 $
b1001 )
b1001 '
#850
1:
04
b100 !
b100 *
b100 1
07
1/
03
16
b1010 +
b1010 -
b1010 $
b1010 )
b1010 '
#855
b101 !
b101 *
b101 1
14
13
b1011 +
b1011 -
b1011 $
b1011 )
b1011 '
#860
0=
0.
04
17
0/
b110 !
b110 *
b110 1
1:
03
06
19
b1100 +
b1100 -
b1100 $
b1100 )
b1100 '
#865
b111 !
b111 *
b111 1
14
13
b1101 +
b1101 -
b1101 $
b1101 )
b1101 '
#870
1=
0:
1.
04
b1000 !
b1000 *
b1000 1
07
1/
03
16
b1110 +
b1110 -
b1110 $
b1110 )
b1110 '
#875
b1001 !
b1001 *
b1001 1
14
13
b1111 +
b1111 -
b1111 $
b1111 )
b1111 '
#880
17
0.
0/
0:
1=
0"
03
06
09
0<
00
b0 +
b0 -
b1011 !
b1011 *
b1011 1
14
12
b0 $
b0 )
b1011 #
b1011 (
b1011 ,
b1011 &
b0 '
#885
1:
07
1/
b1100 !
b1100 *
b1100 1
04
10
13
b1 +
b1 -
b1 $
b1 )
b1 '
#890
14
00
b1101 !
b1101 *
b1101 1
07
03
16
b10 +
b10 -
b10 $
b10 )
b10 '
#895
17
b1110 !
b1110 *
b1110 1
04
10
13
b11 +
b11 -
b11 $
b11 )
b11 '
#900
1=
0"
0.
14
00
17
0/
b1111 !
b1111 *
b1111 1
1:
03
06
19
b100 +
b100 -
b100 $
b100 )
b100 '
#905
0=
1"
0:
1.
07
1/
b0 !
b0 *
b0 1
04
10
13
b101 +
b101 -
b101 $
b101 )
b101 '
#910
14
00
b1 !
b1 *
b1 1
07
03
16
b110 +
b110 -
b110 $
b110 )
b110 '
#915
17
b10 !
b10 *
b10 1
04
10
13
b111 +
b111 -
b111 $
b111 )
b111 '
#920
0.
14
00
17
0/
0:
b11 !
b11 *
b11 1
0=
03
06
09
1<
b1000 +
b1000 -
b1000 $
b1000 )
b1000 '
#925
1:
07
1/
b100 !
b100 *
b100 1
04
10
13
b1001 +
b1001 -
b1001 $
b1001 )
b1001 '
#930
14
00
b101 !
b101 *
b101 1
07
03
16
b1010 +
b1010 -
b1010 $
b1010 )
b1010 '
#935
17
b110 !
b110 *
b110 1
04
10
13
b1011 +
b1011 -
b1011 $
b1011 )
b1011 '
#940
0=
0.
14
00
17
0/
b111 !
b111 *
b111 1
1:
03
06
19
b1100 +
b1100 -
b1100 $
b1100 )
b1100 '
#945
1=
0:
1.
07
1/
b1000 !
b1000 *
b1000 1
04
10
13
b1101 +
b1101 -
b1101 $
b1101 )
b1101 '
#950
14
00
b1001 !
b1001 *
b1001 1
07
03
16
b1110 +
b1110 -
b1110 $
b1110 )
b1110 '
#955
17
b1010 !
b1010 *
b1010 1
04
10
13
b1111 +
b1111 -
b1111 $
b1111 )
b1111 '
#960
0.
1=
0"
03
06
09
0<
00
0/
b0 +
b0 -
04
07
b1100 !
b1100 *
b1100 1
1:
02
05
18
b0 $
b0 )
b1100 #
b1100 (
b1100 ,
b1100 &
b0 '
#965
b1101 !
b1101 *
b1101 1
14
13
b1 +
b1 -
b1 $
b1 )
b1 '
#970
04
b1110 !
b1110 *
b1110 1
17
03
16
b10 +
b10 -
b10 $
b10 )
b10 '
#975
b1111 !
b1111 *
b1111 1
14
13
b11 +
b11 -
b11 $
b11 )
b11 '
#980
0=
1"
04
07
b0 !
b0 *
b0 1
0:
1.
03
06
19
b100 +
b100 -
b100 $
b100 )
b100 '
#985
b1 !
b1 *
b1 1
14
13
b101 +
b101 -
b101 $
b101 )
b101 '
#990
04
b10 !
b10 *
b10 1
17
03
16
b110 +
b110 -
b110 $
b110 )
b110 '
#995
b11 !
b11 *
b11 1
14
13
b111 +
b111 -
b111 $
b111 )
b111 '
